<soapenv:Envelope xmlns:soapenv="http://schemas.xmlsoap.org/soap/envelope/" xmlns:xsi="http://www.w3.org/2001/XMLSchema-instance">
	<soapenv:Header/>
	<soapenv:Body>
		<getWorkOrderInfoBySvcInstIdResponse xmlns="http://pegasus/WsEsm">
			<workOrderInfoResult xmlns="" xmlns:ns1="http://pegasus/WsEsm">
				<ns1:workOrderList>
					<ns1:workOrdNo>XOP5892001</ns1:workOrdNo>
					<ns1:workOrdDtls>
						<ns1:workOrdNo>XOP5892001</ns1:workOrdNo>
						<ns1:svcOrdNo>XOP5892</ns1:svcOrdNo>
						<ns1:svcInstId>252765017</ns1:svcInstId>
						<ns1:acctId/>
						<ns1:billEffectiveDt>24/12/2019</ns1:billEffectiveDt>
						<ns1:custReqDt>24/12/2019</ns1:custReqDt>
						<ns1:jobEffectiveDt>24/12/2019</ns1:jobEffectiveDt>
						<ns1:disconnectReason/>
						<ns1:disconnectCd/>
						<ns1:ordPriority>1</ns1:ordPriority>
						<ns1:svcActionTy>0</ns1:svcActionTy>
						<ns1:workOrdCompletionDt>24/12/2019</ns1:workOrdCompletionDt>
						<ns1:workOrdCreateDt xsi:nil="1"/>
						<ns1:workOrdCreateId>mengting</ns1:workOrdCreateId>
						<ns1:workOrdStatus>4</ns1:workOrdStatus>
						<ns1:workOrdTy>1</ns1:workOrdTy>
						<ns1:cancelledDt xsi:nil="1"/>
						<ns1:cancelledCd/>
						<ns1:cancelledReason/>
					</ns1:workOrdDtls>
					<ns1:ntwkOrdDtls>
						<ns1:nwTxnId>3030778758</ns1:nwTxnId>
						<ns1:nwPrdCd>MOB0001</ns1:nwPrdCd>
						<ns1:nwPrdDesc>Voice Mainline</ns1:nwPrdDesc>
						<ns1:nwPrdAction>1</ns1:nwPrdAction>
						<ns1:startDt/>
						<ns1:endDt/>
						<ns1:nwTxnStatus>1</ns1:nwTxnStatus>
						<ns1:immediateCloseInd>N</ns1:immediateCloseInd>
						<ns1:lineNo>1</ns1:lineNo>
						<ns1:nwOrdParam>
							<ns1:paramNm>ClassSvc</ns1:paramNm>
							<ns1:paramVal>2</ns1:paramVal>
						</ns1:nwOrdParam>
						<ns1:nwOrdParam>
							<ns1:paramNm>EffDt</ns1:paramNm>
							<ns1:paramVal>2019-12-24</ns1:paramVal>
						</ns1:nwOrdParam>
						<ns1:nwOrdParam>
							<ns1:paramNm>EmpId</ns1:paramNm>
							<ns1:paramVal/>
						</ns1:nwOrdParam>
						<ns1:nwOrdParam>
							<ns1:paramNm>IMSINo</ns1:paramNm>
							<ns1:paramVal>525016114566777</ns1:paramVal>
						</ns1:nwOrdParam>
						<ns1:nwOrdParam>
							<ns1:paramNm>LastIMSINo</ns1:paramNm>
							<ns1:paramVal/>
						</ns1:nwOrdParam>
						<ns1:nwOrdParam>
							<ns1:paramNm>NumType</ns1:paramNm>
							<ns1:paramVal/>
						</ns1:nwOrdParam>
						<ns1:nwOrdParam>
							<ns1:paramNm>PMUCd</ns1:paramNm>
							<ns1:paramVal>12</ns1:paramVal>
						</ns1:nwOrdParam>
						<ns1:nwOrdParam>
							<ns1:paramNm>SvcNo</ns1:paramNm>
							<ns1:paramVal>99001425</ns1:paramVal>
						</ns1:nwOrdParam>
					</ns1:ntwkOrdDtls>
					<ns1:ntwkOrdDtls>
						<ns1:nwTxnId>3030778760</ns1:nwTxnId>
						<ns1:nwPrdCd>MOB0017</ns1:nwPrdCd>
						<ns1:nwPrdDesc>Dual Band</ns1:nwPrdDesc>
						<ns1:nwPrdAction>1</ns1:nwPrdAction>
						<ns1:startDt/>
						<ns1:endDt/>
						<ns1:nwTxnStatus>1</ns1:nwTxnStatus>
						<ns1:immediateCloseInd>N</ns1:immediateCloseInd>
						<ns1:lineNo>1</ns1:lineNo>
					</ns1:ntwkOrdDtls>
					<ns1:ntwkOrdDtls>
						<ns1:nwTxnId>3030778764</ns1:nwTxnId>
						<ns1:nwPrdCd>MOB0069</ns1:nwPrdCd>
						<ns1:nwPrdDesc>3G - GPRS Service</ns1:nwPrdDesc>
						<ns1:nwPrdAction>1</ns1:nwPrdAction>
						<ns1:startDt/>
						<ns1:endDt/>
						<ns1:nwTxnStatus>1</ns1:nwTxnStatus>
						<ns1:immediateCloseInd>N</ns1:immediateCloseInd>
						<ns1:lineNo>1</ns1:lineNo>
						<ns1:nwOrdParam>
							<ns1:paramNm>APNID</ns1:paramNm>
							<ns1:paramVal>0000</ns1:paramVal>
						</ns1:nwOrdParam>
						<ns1:nwOrdParam>
							<ns1:paramNm>Class</ns1:paramNm>
							<ns1:paramVal>DF</ns1:paramVal>
						</ns1:nwOrdParam>
						<ns1:nwOrdParam>
							<ns1:paramNm>PDPADD</ns1:paramNm>
							<ns1:paramVal>000000000000</ns1:paramVal>
						</ns1:nwOrdParam>
						<ns1:nwOrdParam>
							<ns1:paramNm>PDPID</ns1:paramNm>
							<ns1:paramVal>1</ns1:paramVal>
						</ns1:nwOrdParam>
						<ns1:nwOrdParam>
							<ns1:paramNm>QOS</ns1:paramNm>
							<ns1:paramVal>509</ns1:paramVal>
						</ns1:nwOrdParam>
					</ns1:ntwkOrdDtls>
					<ns1:ntwkOrdDtls>
						<ns1:nwTxnId>3030778762</ns1:nwTxnId>
						<ns1:nwPrdCd>MOB0067</ns1:nwPrdCd>
						<ns1:nwPrdDesc>Video Streaming</ns1:nwPrdDesc>
						<ns1:nwPrdAction>1</ns1:nwPrdAction>
						<ns1:startDt/>
						<ns1:endDt/>
						<ns1:nwTxnStatus>1</ns1:nwTxnStatus>
						<ns1:immediateCloseInd>N</ns1:immediateCloseInd>
						<ns1:lineNo>1</ns1:lineNo>
					</ns1:ntwkOrdDtls>
					<ns1:ntwkOrdDtls>
						<ns1:nwTxnId>3030778763</ns1:nwTxnId>
						<ns1:nwPrdCd>MOB0068</ns1:nwPrdCd>
						<ns1:nwPrdDesc>MMS</ns1:nwPrdDesc>
						<ns1:nwPrdAction>1</ns1:nwPrdAction>
						<ns1:startDt/>
						<ns1:endDt/>
						<ns1:nwTxnStatus>1</ns1:nwTxnStatus>
						<ns1:immediateCloseInd>N</ns1:immediateCloseInd>
						<ns1:lineNo>1</ns1:lineNo>
					</ns1:ntwkOrdDtls>
					<ns1:ntwkOrdDtls>
						<ns1:nwTxnId>3030778759</ns1:nwTxnId>
						<ns1:nwPrdCd>MOB0010</ns1:nwPrdCd>
						<ns1:nwPrdDesc>Smart Messaging</ns1:nwPrdDesc>
						<ns1:nwPrdAction>1</ns1:nwPrdAction>
						<ns1:startDt/>
						<ns1:endDt/>
						<ns1:nwTxnStatus>1</ns1:nwTxnStatus>
						<ns1:immediateCloseInd>N</ns1:immediateCloseInd>
						<ns1:lineNo>1</ns1:lineNo>
					</ns1:ntwkOrdDtls>
					<ns1:ntwkOrdDtls>
						<ns1:nwTxnId>3030778761</ns1:nwTxnId>
						<ns1:nwPrdCd>MOB0066</ns1:nwPrdCd>
						<ns1:nwPrdDesc>Video Telephony</ns1:nwPrdDesc>
						<ns1:nwPrdAction>1</ns1:nwPrdAction>
						<ns1:startDt/>
						<ns1:endDt/>
						<ns1:nwTxnStatus>1</ns1:nwTxnStatus>
						<ns1:immediateCloseInd>N</ns1:immediateCloseInd>
						<ns1:lineNo>1</ns1:lineNo>
					</ns1:ntwkOrdDtls>
				</ns1:workOrderList>
				<ns1:returnStatus>true</ns1:returnStatus>
			</workOrderInfoResult>
		</getWorkOrderInfoBySvcInstIdResponse>
	</soapenv:Body>
</soapenv:Envelope>